CHANGES.txt
MANIFEST.in
README.md
setup.cfg
setup.py
kaizen_mapping/__init__.py
kaizen_mapping.egg-info/PKG-INFO
kaizen_mapping.egg-info/SOURCES.txt
kaizen_mapping.egg-info/dependency_links.txt
kaizen_mapping.egg-info/requires.txt
kaizen_mapping.egg-info/top_level.txt
kaizen_mapping/map/__init__.py
kaizen_mapping/map/grid.py
kaizen_mapping/map/ict.py
kaizen_mapping/map/matcher.py
kaizen_mapping/map/navigator.py
kaizen_mapping/map/road.py
kaizen_mapping/map/robot.py
kaizen_mapping/map/trace.py
kaizen_mapping/utils/__init__.py
kaizen_mapping/utils/gis.py
kaizen_mapping/utils/numerical.py