Metadata-Version: 2.1
Name: kaizen-mapping
Version: 0.0.1
Summary: Map Matching and road Building Conflict solving Library
Home-page: https://github.com/fuzailpalnak/kaizen
Author: Fuzail Palnak
Author-email: fuzailpalnak@gmail.com
License: UNKNOWN
Keywords: GIS, Map Matching, Road Network, Building Footprint, Polygon, MultiPolygon, Geometry, Iterative Closet Point
Platform: UNKNOWN
Classifier: Programming Language :: Python :: 3
Classifier: License :: OSI Approved :: MIT License
Classifier: Topic :: Software Development :: Libraries
Classifier: Topic :: Software Development :: Libraries :: Python Modules
Classifier: Intended Audience :: Developers
Classifier: Operating System :: OS Independent
Requires-Python: ~=3.3
